hrthy_core/__init__.py
hrthy_core/events/__init__.py
hrthy_core/events/event_mapper.py
hrthy_core/events/topic.py
hrthy_core/events/consumer/__init__.py
hrthy_core/events/consumer/consumer.py
hrthy_core/events/events/__init__.py
hrthy_core/events/events/base_event.py
hrthy_core/events/events/candidate_event.py
hrthy_core/events/events/company_event.py
hrthy_core/events/events/license_event.py
hrthy_core/events/events/notification_event.py
hrthy_core/events/events/payment_event.py
hrthy_core/events/events/pipeline_candidate_event.py
hrthy_core/events/events/pipeline_event.py
hrthy_core/events/events/pipeline_manager_event.py
hrthy_core/events/events/pipeline_step_candidate_event.py
hrthy_core/events/events/pipeline_step_event.py
hrthy_core/events/events/role_event.py
hrthy_core/events/events/user_event.py
hrthy_core/events/producer/__init__.py
hrthy_core/events/producer/producer.py
hrthy_core/http/__init__.py
hrthy_core/http/base_client.py
hrthy_core/http/exceptions.py
hrthy_core/models/__init__.py
hrthy_core/models/base_model.py
hrthy_core/models/constants.py
hrthy_core/models/transaction.py
hrthy_core/models/ts_vector.py
hrthy_core/rate_limit/__init__.py
hrthy_core/rate_limit/exceptions.py
hrthy_core/rate_limit/rate_limit_configuration.py
hrthy_core/rate_limit/rate_limiter.py
hrthy_core/repository/__init__.py
hrthy_core/repository/utils.py
hrthy_core/repository/event/__init__.py
hrthy_core/repository/event/repository.py
hrthy_core/repository/event/repository_abstract.py
hrthy_core/request/__init__.py
hrthy_core/request/exceptions.py
hrthy_core/request/input.py
hrthy_core/request/output.py
hrthy_core/security/__init__.py
hrthy_core/security/constants.py
hrthy_core/security/exceptions.py
hrthy_core/security/scope_checker.py
hrthy_core/security/scopes.py
hrthy_core/security/scopes_configuration.py
hrthy_core/security/scopes_description.py
hrthy_core/security/scopes_hierarchy.py
hrthy_core/security/security.py
hrthy_core/security/settings.py
hrthy.core-1.1.80.dist-info/METADATA
hrthy.core-1.1.80.dist-info/WHEEL
hrthy.core-1.1.80.dist-info/top_level.txt
hrthy.core-1.1.80.dist-info/RECORD
