Metadata-Version: 2.1
Name: hrthy.core
Version: 1.1.80
Summary: Core SDK for Hrthy Project
Home-page: https://github.com/lorenzocastelli/hrthy-core
Author: Lorenzo Castelli
License: MIT
Project-URL: Source, https://github.com/lorenzocastelli/hrthy-core
Platform: UNKNOWN
Requires-Python: >=3.8.3
Requires-Dist: SQLAlchemy (<2,>=1.4.39)
Requires-Dist: fastapi (<1,>=0.79.0)
Requires-Dist: kafka-python (>=2.0.2<3)
Requires-Dist: python-jose[cryptography] (<4,>=3.3.0)
Requires-Dist: requests (>=2.28.1<3)
